{"data":[{"cd":"0001","nm":"동서울"},{"cd":"0511601","nm":"동서울"},{"cd":"1010","nm":"성남"},{"cd":"1012","nm":"수원터미널"},{"cd":"1015","nm":"안산"},{"cd":"1023","nm":"오산"},{"cd":"1045001","nm":"고양(백석)"},{"cd":"1349701","nm":"성남"},{"cd":"1529901","nm":"안산터미널"},{"cd":"1658501","nm":"수원터미널"},{"cd":"1782","nm":"고양종합터미널"},{"cd":"1813701","nm":"오산"},{"cd":"2224201","nm":"인천"},{"cd":"2238201","nm":"인천공항1터미널"},{"cd":"2238202","nm":"인천공항2터미널"},{"cd":"2839701","nm":"청주"},{"cd":"2863501","nm":"남청주"},{"cd":"3010701","nm":"세종청사"},{"cd":"3015","nm":"청주"},{"cd":"3015401","nm":"세종"},{"cd":"3102","nm":"남청주"},{"cd":"3112001","nm":"천안"},{"cd":"3196001","nm":"해미"},{"cd":"3198101","nm":"서산"},{"cd":"3214401","nm":"태안"},{"cd":"3345801","nm":"보령(대천)"},{"cd":"3417501","nm":"유성시외"},{"cd":"3455101","nm":"대전복합"},{"cd":"3776001","nm":"포항"},{"cd":"3815701","nm":"경주시외"},{"cd":"4006","nm":"당진"},{"cd":"4010","nm":"서산"},{"cd":"4018","nm":"장항"},{"cd":"4019","nm":"천안"},{"cd":"4021","nm":"태안"},{"cd":"4024","nm":"보령"},{"cd":"4033","nm":"해미"},{"cd":"4036","nm":"고북"},{"cd":"4045","nm":"서천"},{"cd":"4108","nm":"웅천"},{"cd":"4109","nm":"남포"},{"cd":"4194","nm":"종천"},{"cd":"4200","nm":"주산"},{"cd":"4201","nm":"비인"},{"cd":"4248201","nm":"대구서부"},{"cd":"4255","nm":"어송"},{"cd":"4292","nm":"세종시"},{"cd":"4318","nm":"세종청사"},{"cd":"4319","nm":"내포"},{"cd":"4472001","nm":"울산"},{"cd":"4620401","nm":"부산동부"},{"cd":"5007","nm":"경주시외터미널"},{"cd":"5062901","nm":"양산"},{"cd":"5071","nm":"포항"},{"cd":"5093801","nm":"김해"},{"cd":"5135601","nm":"마산"},{"cd":"5490001","nm":"덕진동"},{"cd":"5493301","nm":"전주시외터미널"},{"cd":"6006","nm":"김해"},{"cd":"6010","nm":"마산"},{"cd":"6018","nm":"양산"},{"cd":"6193701","nm":"광주(유·스퀘어)"},{"cd":"7003","nm":"고창"},{"cd":"7009","nm":"김제"},{"cd":"7013","nm":"대야"},{"cd":"7018","nm":"부안"},{"cd":"7026","nm":"익산"},{"cd":"7033","nm":"전주"},{"cd":"7038","nm":"흥덕"},{"cd":"7069","nm":"만경"},{"cd":"7084","nm":"정읍"},{"cd":"7085","nm":"덕진동"},{"cd":"7174","nm":"완주혁신도시"},{"cd":"7183","nm":"국민연금공단"},{"cd":"7337","nm":"익산역"},{"cd":"8024","nm":"목포"},{"cd":"8025","nm":"무안"},{"cd":"8045","nm":"영광"},{"cd":"8061","nm":"함평"},{"cd":"9001","nm":"부산동부(노포)"},{"cd":"9204","nm":"대구서부"},{"cd":"9302","nm":"인천"},{"cd":"9303","nm":"인천공항T1"},{"cd":"9337","nm":"인천공항T2"},{"cd":"9401","nm":"광주(유ㆍ스퀘어)"},{"cd":"9502","nm":"유성시외"},{"cd":"9503","nm":"대전복합"},{"cd":"9601","nm":"울산"},{"cd":"9614","nm":"울산신복"}]}