{"data":[{"cd":"0001","nm":"동서울"},{"cd":"0511601","nm":"동서울"},{"cd":"2001","nm":"간성"},{"cd":"2019","nm":"속초"},{"cd":"2022","nm":"양구"},{"cd":"2024","nm":"양양"},{"cd":"2028","nm":"원주"},{"cd":"2029","nm":"원통"},{"cd":"2037","nm":"춘천"},{"cd":"2044","nm":"홍천"},{"cd":"2047","nm":"횡성"},{"cd":"2058","nm":"공근"},{"cd":"2060","nm":"백담사입구"},{"cd":"2062","nm":"신남"},{"cd":"2064","nm":"오색"},{"cd":"2065","nm":"장수대"},{"cd":"2066","nm":"장신리"},{"cd":"2067","nm":"진부령"},{"cd":"2111","nm":"낙산"},{"cd":"2112","nm":"물치"},{"cd":"2126","nm":"용대리"},{"cd":"2216","nm":"한계령"},{"cd":"2672","nm":"남교"},{"cd":"9503","nm":"대전복합"}]}